<?xml version="1.0"?>
<col:collection xmlns="http://cnx.rice.edu/collxml" xmlns:col="http://cnx.rice.edu/collxml" xml:lang="en" authors="Mordechai (Moti) Ben-Ari">
  <metadata xmlns:md="http://cnx.rice.edu/mdml" mdml-version="0.5">
    <md:content-id>col10913</md:content-id>
    <md:title>Compile and Runtime Errors in Java</md:title>
    <md:license url="http://creativecommons.org/licenses/by/3.0/">Creative Commons Attribution License 3.0</md:license>
    <md:language>en</md:language>
    <md:uuid>7fc9706e-34b8-49f8-b8ec-94389026cf94</md:uuid>
    <md:slug>compile-and-runtime-errors-in-java</md:slug>
  </metadata>
  <col:content>
    <col:module document="m31180"/>
    <col:module document="m31181"/>
    <col:module document="m31182"/>
    <col:module document="m31183"/>
    <col:module document="m31184"/>
    <col:module document="m31186"/>
    <col:module document="m31187"/>
    <col:module document="m31188"/>
  </col:content>
</col:collection>
